{
  "model": "meta-llama/Meta-Llama-3-8B-Instruct",
  "n_layers": 32,
  "num_prompts": 100,
  "vector_path": "EasySteer/replications/creative_writing/create.gguf",
  "per_site": [
    {
      "site_i": 0,
      "layer_idx": -1,
      "mu_norm": 0.128936305642128,
      "tr_sigma": 0.2068416178226471,
      "e_norm": 0.45991626381874084,
      "max_norm": 0.7488673329353333,
      "cos_ref_mu": null
    },
    {
      "site_i": 1,
      "layer_idx": 0,
      "mu_norm": 0.3624427616596222,
      "tr_sigma": 0.9829719066619873,
      "e_norm": 0.9026306867599487,
      "max_norm": 8.329346656799316,
      "cos_ref_mu": 0.08468829095363617
    },
    {
      "site_i": 2,
      "layer_idx": 1,
      "mu_norm": 1.8465609550476074,
      "tr_sigma": 711.0203857421875,
      "e_norm": 3.11861252784729,
      "max_norm": 388.2984313964844,
      "cos_ref_mu": 0.004981838166713715
    },
    {
      "site_i": 3,
      "layer_idx": 2,
      "mu_norm": 1.9279658794403076,
      "tr_sigma": 712.7530517578125,
      "e_norm": 3.692497968673706,
      "max_norm": 388.3558349609375,
      "cos_ref_mu": 0.018780488520860672
    },
    {
      "site_i": 4,
      "layer_idx": 3,
      "mu_norm": 2.0377962589263916,
      "tr_sigma": 715.4244384765625,
      "e_norm": 4.326826572418213,
      "max_norm": 388.4419860839844,
      "cos_ref_mu": 0.04721246659755707
    },
    {
      "site_i": 5,
      "layer_idx": 4,
      "mu_norm": 2.1494789123535156,
      "tr_sigma": 718.77734375,
      "e_norm": 4.940013885498047,
      "max_norm": 388.542724609375,
      "cos_ref_mu": 0.0703519731760025
    },
    {
      "site_i": 6,
      "layer_idx": 5,
      "mu_norm": 2.2910194396972656,
      "tr_sigma": 722.3695678710938,
      "e_norm": 5.490408897399902,
      "max_norm": 388.6677551269531,
      "cos_ref_mu": 0.02401835098862648
    },
    {
      "site_i": 7,
      "layer_idx": 6,
      "mu_norm": 2.4056057929992676,
      "tr_sigma": 726.1333618164062,
      "e_norm": 5.9897308349609375,
      "max_norm": 388.7585754394531,
      "cos_ref_mu": -0.02905651554465294
    },
    {
      "site_i": 8,
      "layer_idx": 7,
      "mu_norm": 2.4839890003204346,
      "tr_sigma": 730.1137084960938,
      "e_norm": 6.433224201202393,
      "max_norm": 388.8730163574219,
      "cos_ref_mu": 0.020630650222301483
    },
    {
      "site_i": 9,
      "layer_idx": 8,
      "mu_norm": 2.5922882556915283,
      "tr_sigma": 733.1768798828125,
      "e_norm": 6.777984142303467,
      "max_norm": 388.9610595703125,
      "cos_ref_mu": 0.01463193167001009
    },
    {
      "site_i": 10,
      "layer_idx": 9,
      "mu_norm": 2.7843832969665527,
      "tr_sigma": 736.6884765625,
      "e_norm": 7.200106620788574,
      "max_norm": 389.0162048339844,
      "cos_ref_mu": 0.007315510883927345
    },
    {
      "site_i": 11,
      "layer_idx": 10,
      "mu_norm": 2.807615280151367,
      "tr_sigma": 745.3487548828125,
      "e_norm": 7.462881088256836,
      "max_norm": 390.6427001953125,
      "cos_ref_mu": 0.07017134875059128
    },
    {
      "site_i": 12,
      "layer_idx": 11,
      "mu_norm": 2.8759498596191406,
      "tr_sigma": 747.561279296875,
      "e_norm": 7.672628879547119,
      "max_norm": 390.6680908203125,
      "cos_ref_mu": 0.008399338461458683
    },
    {
      "site_i": 13,
      "layer_idx": 12,
      "mu_norm": 3.259903907775879,
      "tr_sigma": 751.7756958007812,
      "e_norm": 8.169828414916992,
      "max_norm": 390.7812194824219,
      "cos_ref_mu": 0.057208795100450516
    },
    {
      "site_i": 14,
      "layer_idx": 13,
      "mu_norm": 3.4518651962280273,
      "tr_sigma": 757.594482421875,
      "e_norm": 8.689519882202148,
      "max_norm": 390.86053466796875,
      "cos_ref_mu": 0.034053824841976166
    },
    {
      "site_i": 15,
      "layer_idx": 14,
      "mu_norm": 3.5872690677642822,
      "tr_sigma": 765.2103271484375,
      "e_norm": 9.271113395690918,
      "max_norm": 390.90972900390625,
      "cos_ref_mu": 0.06800641864538193
    },
    {
      "site_i": 16,
      "layer_idx": 15,
      "mu_norm": 3.813385248184204,
      "tr_sigma": 778.206298828125,
      "e_norm": 10.192914009094238,
      "max_norm": 390.88494873046875,
      "cos_ref_mu": 0.05539020150899887
    },
    {
      "site_i": 17,
      "layer_idx": 16,
      "mu_norm": 4.2863640785217285,
      "tr_sigma": 792.7288818359375,
      "e_norm": 11.195590019226074,
      "max_norm": 390.979248046875,
      "cos_ref_mu": 0.042947567999362946
    },
    {
      "site_i": 18,
      "layer_idx": 17,
      "mu_norm": 4.476078510284424,
      "tr_sigma": 815.494384765625,
      "e_norm": 12.381781578063965,
      "max_norm": 391.12884521484375,
      "cos_ref_mu": 0.022604234516620636
    },
    {
      "site_i": 19,
      "layer_idx": 18,
      "mu_norm": 4.899759769439697,
      "tr_sigma": 837.82958984375,
      "e_norm": 13.542335510253906,
      "max_norm": 391.1761169433594,
      "cos_ref_mu": -0.0039027021266520023
    },
    {
      "site_i": 20,
      "layer_idx": 19,
      "mu_norm": 5.553990364074707,
      "tr_sigma": 860.060546875,
      "e_norm": 14.703097343444824,
      "max_norm": 391.19482421875,
      "cos_ref_mu": -0.02566882222890854
    },
    {
      "site_i": 21,
      "layer_idx": 20,
      "mu_norm": 5.845177173614502,
      "tr_sigma": 887.2484741210938,
      "e_norm": 15.824572563171387,
      "max_norm": 391.1482238769531,
      "cos_ref_mu": -0.042684752494096756
    },
    {
      "site_i": 22,
      "layer_idx": 21,
      "mu_norm": 6.520715236663818,
      "tr_sigma": 935.7350463867188,
      "e_norm": 17.674137115478516,
      "max_norm": 391.1914978027344,
      "cos_ref_mu": -0.09355398267507553
    },
    {
      "site_i": 23,
      "layer_idx": 22,
      "mu_norm": 7.3275556564331055,
      "tr_sigma": 981.4512329101562,
      "e_norm": 19.330055236816406,
      "max_norm": 391.193359375,
      "cos_ref_mu": -0.086894690990448
    },
    {
      "site_i": 24,
      "layer_idx": 23,
      "mu_norm": 8.474807739257812,
      "tr_sigma": 1034.204833984375,
      "e_norm": 21.185611724853516,
      "max_norm": 391.216796875,
      "cos_ref_mu": -0.10172896832227707
    },
    {
      "site_i": 25,
      "layer_idx": 24,
      "mu_norm": 9.68553352355957,
      "tr_sigma": 1085.220947265625,
      "e_norm": 22.939189910888672,
      "max_norm": 391.19464111328125,
      "cos_ref_mu": -0.08375529944896698
    },
    {
      "site_i": 26,
      "layer_idx": 25,
      "mu_norm": 10.65548324584961,
      "tr_sigma": 1146.2557373046875,
      "e_norm": 24.734146118164062,
      "max_norm": 391.1578674316406,
      "cos_ref_mu": -0.02923610806465149
    },
    {
      "site_i": 27,
      "layer_idx": 26,
      "mu_norm": 12.90756607055664,
      "tr_sigma": 1217.94287109375,
      "e_norm": 27.232454299926758,
      "max_norm": 391.229736328125,
      "cos_ref_mu": -0.011236460879445076
    },
    {
      "site_i": 28,
      "layer_idx": 27,
      "mu_norm": 14.67172622680664,
      "tr_sigma": 1295.8515625,
      "e_norm": 29.576879501342773,
      "max_norm": 390.9627990722656,
      "cos_ref_mu": 0.014225204475224018
    },
    {
      "site_i": 29,
      "layer_idx": 28,
      "mu_norm": 16.738056182861328,
      "tr_sigma": 1408.84912109375,
      "e_norm": 32.570858001708984,
      "max_norm": 390.8322448730469,
      "cos_ref_mu": 0.025841981172561646
    },
    {
      "site_i": 30,
      "layer_idx": 29,
      "mu_norm": 18.649534225463867,
      "tr_sigma": 1553.427734375,
      "e_norm": 35.844303131103516,
      "max_norm": 390.3286437988281,
      "cos_ref_mu": 0.06818129867315292
    },
    {
      "site_i": 31,
      "layer_idx": 30,
      "mu_norm": 19.75078582763672,
      "tr_sigma": 1782.3875732421875,
      "e_norm": 39.7401237487793,
      "max_norm": 387.04302978515625,
      "cos_ref_mu": 0.04200614243745804
    },
    {
      "site_i": 32,
      "layer_idx": 31,
      "mu_norm": 18.919179916381836,
      "tr_sigma": 2180.154052734375,
      "e_norm": 49.10264587402344,
      "max_norm": 287.3090515136719,
      "cos_ref_mu": 0.006652806885540485
    }
  ]
}